tests/test_gcp_secret_manager.py
tests/test_vault_client.py
vaultlock_py-0.1.2.dist-info/METADATA
vaultlock_py-0.1.2.dist-info/WHEEL
vaultlock_py-0.1.2.dist-info/entry_points.txt
vaultlock_py-0.1.2.dist-info/top_level.txt
vaultlock_py-0.1.2.dist-info/RECORD
