Metadata-Version: 2.4
Name: vaultlock-py
Version: 0.1.2
Summary: Secure secrets and encryption manager for GCP Secret Manager, Vault, and KMS
Author-email: Raghava Chellu <raghava.chellu@gmail.com>
License: MIT
Keywords: vault,gcp,kms,secret-manager,cryptography,key-management,linux,google-cloud,security,encryption,python,cli,devsecops
Classifier: Programming Language :: Python :: 3
Classifier: Operating System :: OS Independent
Classifier: Topic :: Security :: Cryptography
Classifier: Intended Audience :: Developers
Classifier: Development Status :: 4 - Beta
Requires-Python: >=3.8
Requires-Dist: google-cloud-secret-manager
Requires-Dist: google-cloud-kms
Requires-Dist: hvac
